LICENSE
MANIFEST.in
README.md
README.rst
setup.py
nbviewer/__init__.py
nbviewer/nbviewer.py
notebook_viewer.egg-info/PKG-INFO
notebook_viewer.egg-info/SOURCES.txt
notebook_viewer.egg-info/dependency_links.txt
notebook_viewer.egg-info/entry_points.txt
notebook_viewer.egg-info/requires.txt
notebook_viewer.egg-info/top_level.txt