Metadata-Version: 1.1
Name: notebook-viewer
Version: 1.0.1
Summary: ipython notebook link generation script
Home-page: https://github.com/tr3buchet/notebook-viewer
Author: Trey Morris
Author-email: trey@treymorris.com
License: Apache Software License
Keywords: github,gist,ipython,notebook,nbviewer
Platform: UNKNOWN
Classifier: Development Status :: 5 - Production/Stable
Classifier: License :: OSI Approved :: Apache Software License
